{
  "id": "00000000-0000-0000-0000-000000000000",
  "prevId": "",
  "version": "5",
  "dialect": "mysql",
  "tables": {
    "User": {
      "name": "User",
      "columns": {
        "id": {
          "autoincrement": true,
          "name": "id",
          "type": "int",
          "primaryKey": false,
          "notNull": true
        },
        "fullName": {
          "autoincrement": false,
          "name": "fullName",
          "type": "varchar(255)",
          "primaryKey": false,
          "notNull": false
        },
        "birthday": {
          "autoincrement": false,
          "name": "birthday",
          "type": "date",
          "primaryKey": false,
          "notNull": false
        },
        "gender": {
          "autoincrement": false,
          "name": "gender",
          "type": "enum('MALE','FEMALE')",
          "primaryKey": false,
          "notNull": false
        },
        "username": {
          "autoincrement": false,
          "name": "username",
          "type": "varchar(255)",
          "primaryKey": false,
          "notNull": false
        },
        "password": {
          "autoincrement": false,
          "name": "password",
          "type": "varchar(255)",
          "primaryKey": false,
          "notNull": false
        }
      },
      "compositePrimaryKeys": {
        "User_id": {
          "name": "User_id",
          "columns": [
            "id"
          ]
        }
      },
      "indexes": {},
      "foreignKeys": {},
      "uniqueConstraints": {}
    },
    "WSET": {
      "name": "WSET",
      "columns": {
        "id": {
          "autoincrement": true,
          "name": "id",
          "type": "int",
          "primaryKey": false,
          "notNull": true
        },
        "aIntensity": {
          "autoincrement": false,
          "name": "aIntensity",
          "type": "enum('Low','Medium','High')",
          "primaryKey": false,
          "notNull": false
        },
        "nIntensity": {
          "autoincrement": false,
          "name": "nIntensity",
          "type": "enum('Low','Medium','High')",
          "primaryKey": false,
          "notNull": false
        },
        "sweetness": {
          "autoincrement": false,
          "name": "sweetness",
          "type": "enum('Dry','Medium','Sweet')",
          "primaryKey": false,
          "notNull": false
        },
        "aromaCharacteristics": {
          "autoincrement": false,
          "name": "aromaCharacteristics",
          "type": "text",
          "primaryKey": false,
          "notNull": false
        },
        "acidity": {
          "autoincrement": false,
          "name": "acidity",
          "type": "enum('Low','Medium','High')",
          "primaryKey": false,
          "notNull": false
        },
        "tannin": {
          "autoincrement": false,
          "name": "tannin",
          "type": "enum('Low','Medium','High')",
          "primaryKey": false,
          "notNull": false
        },
        "alcohol": {
          "autoincrement": false,
          "name": "alcohol",
          "type": "enum('Low','Medium','High')",
          "primaryKey": false,
          "notNull": false
        },
        "body": {
          "autoincrement": false,
          "name": "body",
          "type": "enum('Light','Medium','Full')",
          "primaryKey": false,
          "notNull": false
        },
        "flavourIntensity": {
          "autoincrement": false,
          "name": "flavourIntensity",
          "type": "enum('Low','Medium','High')",
          "primaryKey": false,
          "notNull": false
        },
        "flavourCharacteristics": {
          "autoincrement": false,
          "name": "flavourCharacteristics",
          "type": "text",
          "primaryKey": false,
          "notNull": false
        },
        "finish": {
          "autoincrement": false,
          "name": "finish",
          "type": "enum('Short','Medium','Long')",
          "primaryKey": false,
          "notNull": false
        },
        "quality": {
          "autoincrement": false,
          "name": "quality",
          "type": "enum('Poor','Fair','Good','Very Good','Excellent')",
          "primaryKey": false,
          "notNull": false
        }
      },
      "compositePrimaryKeys": {
        "WSET_id": {
          "name": "WSET_id",
          "columns": [
            "id"
          ]
        }
      },
      "indexes": {},
      "foreignKeys": {},
      "uniqueConstraints": {}
    },
    "Wine": {
      "name": "Wine",
      "columns": {
        "id": {
          "autoincrement": true,
          "name": "id",
          "type": "int",
          "primaryKey": false,
          "notNull": true
        },
        "name": {
          "autoincrement": false,
          "name": "name",
          "type": "varchar(255)",
          "primaryKey": false,
          "notNull": false
        },
        "country": {
          "autoincrement": false,
          "name": "country",
          "type": "varchar(255)",
          "primaryKey": false,
          "notNull": false
        },
        "region": {
          "autoincrement": false,
          "name": "region",
          "type": "varchar(255)",
          "primaryKey": false,
          "notNull": false
        },
        "prodYear": {
          "autoincrement": false,
          "name": "prodYear",
          "type": "date",
          "primaryKey": false,
          "notNull": false
        },
        "producer": {
          "autoincrement": false,
          "name": "producer",
          "type": "varchar(255)",
          "primaryKey": false,
          "notNull": false
        },
        "alcohol": {
          "autoincrement": false,
          "name": "alcohol",
          "type": "decimal(5,2)",
          "primaryKey": false,
          "notNull": false
        },
        "type": {
          "autoincrement": false,
          "name": "type",
          "type": "varchar(255)",
          "primaryKey": false,
          "notNull": false
        },
        "grape": {
          "autoincrement": false,
          "name": "grape",
          "type": "varchar(255)",
          "primaryKey": false,
          "notNull": false
        },
        "price": {
          "autoincrement": false,
          "name": "price",
          "type": "decimal(10,2)",
          "primaryKey": false,
          "notNull": false
        },
        "currency": {
          "autoincrement": false,
          "name": "currency",
          "type": "varchar(3)",
          "primaryKey": false,
          "notNull": false
        }
      },
      "compositePrimaryKeys": {
        "Wine_id": {
          "name": "Wine_id",
          "columns": [
            "id"
          ]
        }
      },
      "indexes": {},
      "foreignKeys": {},
      "uniqueConstraints": {}
    },
    "WineEvaluation": {
      "name": "WineEvaluation",
      "columns": {
        "id": {
          "autoincrement": true,
          "name": "id",
          "type": "int",
          "primaryKey": false,
          "notNull": true
        },
        "wineId": {
          "autoincrement": false,
          "name": "wineId",
          "type": "int",
          "primaryKey": false,
          "notNull": false
        },
        "userId": {
          "autoincrement": false,
          "name": "userId",
          "type": "int",
          "primaryKey": false,
          "notNull": false
        },
        "evaluationName": {
          "autoincrement": false,
          "name": "evaluationName",
          "type": "varchar(255)",
          "primaryKey": false,
          "notNull": false
        },
        "note": {
          "autoincrement": false,
          "name": "note",
          "type": "text",
          "primaryKey": false,
          "notNull": false
        }
      },
      "compositePrimaryKeys": {
        "WineEvaluation_id": {
          "name": "WineEvaluation_id",
          "columns": [
            "id"
          ]
        }
      },
      "indexes": {
        "userId": {
          "name": "userId",
          "columns": [
            "userId"
          ],
          "isUnique": false
        },
        "wineId": {
          "name": "wineId",
          "columns": [
            "wineId"
          ],
          "isUnique": false
        }
      },
      "foreignKeys": {
        "WineEvaluation_ibfk_1": {
          "name": "WineEvaluation_ibfk_1",
          "tableFrom": "WineEvaluation",
          "tableTo": "Wine",
          "columnsFrom": [
            "wineId"
          ],
          "columnsTo": [
            "id"
          ],
          "onDelete": "no action",
          "onUpdate": "no action"
        },
        "WineEvaluation_ibfk_2": {
          "name": "WineEvaluation_ibfk_2",
          "tableFrom": "WineEvaluation",
          "tableTo": "User",
          "columnsFrom": [
            "userId"
          ],
          "columnsTo": [
            "id"
          ],
          "onDelete": "no action",
          "onUpdate": "no action"
        }
      },
      "uniqueConstraints": {}
    },
    "WineTasting": {
      "name": "WineTasting",
      "columns": {
        "id": {
          "autoincrement": true,
          "name": "id",
          "type": "int",
          "primaryKey": false,
          "notNull": true
        },
        "visibility": {
          "autoincrement": false,
          "name": "visibility",
          "type": "enum('Public','Private')",
          "primaryKey": false,
          "notNull": false
        },
        "date": {
          "autoincrement": false,
          "name": "date",
          "type": "date",
          "primaryKey": false,
          "notNull": false
        },
        "hostId": {
          "autoincrement": false,
          "name": "hostId",
          "type": "int",
          "primaryKey": false,
          "notNull": false
        },
        "winnerId": {
          "autoincrement": false,
          "name": "winnerId",
          "type": "int",
          "primaryKey": false,
          "notNull": false
        },
        "finished": {
          "autoincrement": false,
          "name": "finished",
          "type": "tinyint",
          "primaryKey": false,
          "notNull": false
        },
        "title": {
          "autoincrement": false,
          "name": "title",
          "type": "varchar(255)",
          "primaryKey": false,
          "notNull": false
        }
      },
      "compositePrimaryKeys": {
        "WineTasting_id": {
          "name": "WineTasting_id",
          "columns": [
            "id"
          ]
        }
      },
      "indexes": {
        "hostId": {
          "name": "hostId",
          "columns": [
            "hostId"
          ],
          "isUnique": false
        },
        "winnerId": {
          "name": "winnerId",
          "columns": [
            "winnerId"
          ],
          "isUnique": false
        }
      },
      "foreignKeys": {
        "WineTasting_ibfk_1": {
          "name": "WineTasting_ibfk_1",
          "tableFrom": "WineTasting",
          "tableTo": "User",
          "columnsFrom": [
            "hostId"
          ],
          "columnsTo": [
            "id"
          ],
          "onDelete": "no action",
          "onUpdate": "no action"
        },
        "WineTasting_ibfk_2": {
          "name": "WineTasting_ibfk_2",
          "tableFrom": "WineTasting",
          "tableTo": "Wine",
          "columnsFrom": [
            "winnerId"
          ],
          "columnsTo": [
            "id"
          ],
          "onDelete": "no action",
          "onUpdate": "no action"
        }
      },
      "uniqueConstraints": {}
    },
    "WineTasting_Participants": {
      "name": "WineTasting_Participants",
      "columns": {
        "wineTastingId": {
          "autoincrement": false,
          "name": "wineTastingId",
          "type": "int",
          "primaryKey": false,
          "notNull": true
        },
        "userId": {
          "autoincrement": false,
          "name": "userId",
          "type": "int",
          "primaryKey": false,
          "notNull": true
        }
      },
      "compositePrimaryKeys": {
        "WineTasting_Participants_wineTastingId_userId": {
          "name": "WineTasting_Participants_wineTastingId_userId",
          "columns": [
            "wineTastingId",
            "userId"
          ]
        }
      },
      "indexes": {
        "userId": {
          "name": "userId",
          "columns": [
            "userId"
          ],
          "isUnique": false
        }
      },
      "foreignKeys": {
        "WineTasting_Participants_ibfk_1": {
          "name": "WineTasting_Participants_ibfk_1",
          "tableFrom": "WineTasting_Participants",
          "tableTo": "WineTasting",
          "columnsFrom": [
            "wineTastingId"
          ],
          "columnsTo": [
            "id"
          ],
          "onDelete": "no action",
          "onUpdate": "no action"
        },
        "WineTasting_Participants_ibfk_2": {
          "name": "WineTasting_Participants_ibfk_2",
          "tableFrom": "WineTasting_Participants",
          "tableTo": "User",
          "columnsFrom": [
            "userId"
          ],
          "columnsTo": [
            "id"
          ],
          "onDelete": "no action",
          "onUpdate": "no action"
        }
      },
      "uniqueConstraints": {}
    },
    "WineTasting_Wines": {
      "name": "WineTasting_Wines",
      "columns": {
        "wineTastingId": {
          "autoincrement": false,
          "name": "wineTastingId",
          "type": "int",
          "primaryKey": false,
          "notNull": true
        },
        "wineId": {
          "autoincrement": false,
          "name": "wineId",
          "type": "int",
          "primaryKey": false,
          "notNull": true
        }
      },
      "compositePrimaryKeys": {
        "WineTasting_Wines_wineTastingId_wineId": {
          "name": "WineTasting_Wines_wineTastingId_wineId",
          "columns": [
            "wineTastingId",
            "wineId"
          ]
        }
      },
      "indexes": {
        "wineId": {
          "name": "wineId",
          "columns": [
            "wineId"
          ],
          "isUnique": false
        }
      },
      "foreignKeys": {
        "WineTasting_Wines_ibfk_1": {
          "name": "WineTasting_Wines_ibfk_1",
          "tableFrom": "WineTasting_Wines",
          "tableTo": "WineTasting",
          "columnsFrom": [
            "wineTastingId"
          ],
          "columnsTo": [
            "id"
          ],
          "onDelete": "no action",
          "onUpdate": "no action"
        },
        "WineTasting_Wines_ibfk_2": {
          "name": "WineTasting_Wines_ibfk_2",
          "tableFrom": "WineTasting_Wines",
          "tableTo": "Wine",
          "columnsFrom": [
            "wineId"
          ],
          "columnsTo": [
            "id"
          ],
          "onDelete": "no action",
          "onUpdate": "no action"
        }
      },
      "uniqueConstraints": {}
    },
    "_prisma_migrations": {
      "name": "_prisma_migrations",
      "columns": {
        "id": {
          "autoincrement": false,
          "name": "id",
          "type": "varchar(36)",
          "primaryKey": false,
          "notNull": true
        },
        "checksum": {
          "autoincrement": false,
          "name": "checksum",
          "type": "varchar(64)",
          "primaryKey": false,
          "notNull": true
        },
        "finished_at": {
          "autoincrement": false,
          "name": "finished_at",
          "type": "datetime(3)",
          "primaryKey": false,
          "notNull": false
        },
        "migration_name": {
          "autoincrement": false,
          "name": "migration_name",
          "type": "varchar(255)",
          "primaryKey": false,
          "notNull": true
        },
        "logs": {
          "autoincrement": false,
          "name": "logs",
          "type": "text",
          "primaryKey": false,
          "notNull": false
        },
        "rolled_back_at": {
          "autoincrement": false,
          "name": "rolled_back_at",
          "type": "datetime(3)",
          "primaryKey": false,
          "notNull": false
        },
        "started_at": {
          "default": "CURRENT_TIMESTAMP(3)",
          "autoincrement": false,
          "name": "started_at",
          "type": "datetime(3)",
          "primaryKey": false,
          "notNull": true
        },
        "applied_steps_count": {
          "default": 0,
          "autoincrement": false,
          "name": "applied_steps_count",
          "type": "int unsigned",
          "primaryKey": false,
          "notNull": true
        }
      },
      "compositePrimaryKeys": {
        "_prisma_migrations_id": {
          "name": "_prisma_migrations_id",
          "columns": [
            "id"
          ]
        }
      },
      "indexes": {},
      "foreignKeys": {},
      "uniqueConstraints": {}
    }
  },
  "schemas": {},
  "_meta": {
    "schemas": {},
    "tables": {},
    "columns": {}
  }
}